LICENSE
util_captcha/__init__.py
util_captcha/fonts/arial.ttf
util_captcha/image.py
util_captcha/utils.py
util_captcha-0.2.2.dist-info/LICENSE
util_captcha-0.2.2.dist-info/WHEEL
util_captcha-0.2.2.dist-info/METADATA
util_captcha-0.2.2.dist-info/RECORD
