Metadata-Version: 2.1
Name: util-captcha
Version: 0.2.2
Summary: A library that generates image CAPTCHAs.
Home-page: https://gitee.com/full-stack-web/util-captcha
License: MIT
Keywords: util,captcha
Author: punklee333
Author-email: punklee333@gmail.com
Requires-Python: >=3.9,<4.0
Classifier: License :: OSI Approved :: MIT License
Classifier: Programming Language :: Python :: 3
Classifier: Programming Language :: Python :: 3.9
Classifier: Programming Language :: Python :: 3.10
Classifier: Programming Language :: Python :: 3.11
Requires-Dist: pillow (>=9.4.0,<10.0.0)
